{
  "type": "File",
  "start": 0,
  "end": 1944,
  "loc": {
    "start": {
      "line": 1,
      "column": 0
    },
    "end": {
      "line": 50,
      "column": 0
    }
  },
  "program": {
    "type": "Program",
    "start": 0,
    "end": 1944,
    "loc": {
      "start": {
        "line": 1,
        "column": 0
      },
      "end": {
        "line": 50,
        "column": 0
      }
    },
    "sourceType": "module",
    "body": [
      {
        "type": "ImportDeclaration",
        "start": 1544,
        "end": 1580,
        "loc": {
          "start": {
            "line": 31,
            "column": 0
          },
          "end": {
            "line": 31,
            "column": 36
          }
        },
        "specifiers": [
          {
            "type": "ImportSpecifier",
            "start": 1553,
            "end": 1560,
            "loc": {
              "start": {
                "line": 31,
                "column": 9
              },
              "end": {
                "line": 31,
                "column": 16
              }
            },
            "imported": {
              "type": "Identifier",
              "start": 1553,
              "end": 1560,
              "loc": {
                "start": {
                  "line": 31,
                  "column": 9
                },
                "end": {
                  "line": 31,
                  "column": 16
                },
                "identifierName": "Element"
              },
              "name": "Element",
              "leadingComments": null
            },
            "local": {
              "type": "Identifier",
              "start": 1553,
              "end": 1560,
              "loc": {
                "start": {
                  "line": 31,
                  "column": 9
                },
                "end": {
                  "line": 31,
                  "column": 16
                },
                "identifierName": "Element"
              },
              "name": "Element"
            },
            "leadingComments": null
          }
        ],
        "source": {
          "type": "StringLiteral",
          "start": 1568,
          "end": 1579,
          "loc": {
            "start": {
              "line": 31,
              "column": 24
            },
            "end": {
              "line": 31,
              "column": 35
            }
          },
          "extra": {
            "rawValue": "./Element",
            "raw": "\"./Element\""
          },
          "value": "./Element"
        },
        "leadingComments": [
          {
            "type": "CommentBlock",
            "value": "*\n * OS.js - JavaScript Cloud/Web Desktop Platform\n *\n * Copyright (c) 2011-2020, Anders Evenrud <andersevenrud@gmail.com>\n * All rights reserved.\n *\n * Redistribution and use in source and binary forms, with or without\n * modification, are permitted provided that the following conditions are met:\n *\n * 1. Redistributions of source code must retain the above copyright notice, this\n *    list of conditions and the following disclaimer\n * 2. Redistributions in binary form must reproduce the above copyright notice,\n *    this list of conditions and the following disclaimer in the documentation\n *    and/or other materials provided with the distribution\n *\n * THIS SOFTWARE IS PROVIDED BY THE COPYRIGHT HOLDERS AND CONTRIBUTORS \"AS IS\" AND\n * ANY EXPRESS OR IMPLIED WARRANTIES, INCLUDING, BUT NOT LIMITED TO, THE IMPLIED\n * WARRANTIES OF MERCHANTABILITY AND FITNESS FOR A PARTICULAR PURPOSE ARE\n * DISCLAIMED. IN NO EVENT SHALL THE COPYRIGHT OWNER OR CONTRIBUTORS BE LIABLE FOR\n * ANY DIRECT, INDIRECT, INCIDENTAL, SPECIAL, EXEMPLARY, OR CONSEQUENTIAL DAMAGES\n * (INCLUDING, BUT NOT LIMITED TO, PROCUREMENT OF SUBSTITUTE GOODS OR SERVICES;\n * LOSS OF USE, DATA, OR PROFITS; OR BUSINESS INTERRUPTION) HOWEVER CAUSED AND\n * ON ANY THEORY OF LIABILITY, WHETHER IN CONTRACT, STRICT LIABILITY, OR TORT\n * (INCLUDING NEGLIGENCE OR OTHERWISE) ARISING IN ANY WAY OUT OF THE USE OF THIS\n * SOFTWARE, EVEN IF ADVISED OF THE POSSIBILITY OF SUCH DAMAGE.\n *\n * @author  Anders Evenrud <andersevenrud@gmail.com>\n * @licence Simplified BSD License\n ",
            "start": 0,
            "end": 1542,
            "loc": {
              "start": {
                "line": 1,
                "column": 0
              },
              "end": {
                "line": 29,
                "column": 3
              }
            }
          }
        ]
      },
      {
        "type": "ImportDeclaration",
        "start": 1581,
        "end": 1610,
        "loc": {
          "start": {
            "line": 32,
            "column": 0
          },
          "end": {
            "line": 32,
            "column": 29
          }
        },
        "specifiers": [
          {
            "type": "ImportSpecifier",
            "start": 1590,
            "end": 1591,
            "loc": {
              "start": {
                "line": 32,
                "column": 9
              },
              "end": {
                "line": 32,
                "column": 10
              }
            },
            "imported": {
              "type": "Identifier",
              "start": 1590,
              "end": 1591,
              "loc": {
                "start": {
                  "line": 32,
                  "column": 9
                },
                "end": {
                  "line": 32,
                  "column": 10
                },
                "identifierName": "h"
              },
              "name": "h"
            },
            "local": {
              "type": "Identifier",
              "start": 1590,
              "end": 1591,
              "loc": {
                "start": {
                  "line": 32,
                  "column": 9
                },
                "end": {
                  "line": 32,
                  "column": 10
                },
                "identifierName": "h"
              },
              "name": "h"
            }
          }
        ],
        "source": {
          "type": "StringLiteral",
          "start": 1599,
          "end": 1609,
          "loc": {
            "start": {
              "line": 32,
              "column": 18
            },
            "end": {
              "line": 32,
              "column": 28
            }
          },
          "extra": {
            "rawValue": "hyperapp",
            "raw": "\"hyperapp\""
          },
          "value": "hyperapp"
        },
        "trailingComments": [
          {
            "type": "CommentBlock",
            "value": "*\n * A flexbox\n * @param {BoxProperties} props Properties\n * @param {string} [props.orientation='horizontal'] Box orientation\n * @param {h[]} children Children\n ",
            "start": 1612,
            "end": 1777,
            "loc": {
              "start": {
                "line": 34,
                "column": 0
              },
              "end": {
                "line": 39,
                "column": 3
              }
            }
          }
        ]
      },
      {
        "type": "ExportNamedDeclaration",
        "start": 1778,
        "end": 1943,
        "loc": {
          "start": {
            "line": 40,
            "column": 0
          },
          "end": {
            "line": 49,
            "column": 3
          }
        },
        "specifiers": [],
        "source": null,
        "declaration": {
          "type": "VariableDeclaration",
          "start": 1785,
          "end": 1943,
          "loc": {
            "start": {
              "line": 40,
              "column": 7
            },
            "end": {
              "line": 49,
              "column": 3
            }
          },
          "declarations": [
            {
              "type": "VariableDeclarator",
              "start": 1791,
              "end": 1942,
              "loc": {
                "start": {
                  "line": 40,
                  "column": 13
                },
                "end": {
                  "line": 49,
                  "column": 2
                }
              },
              "id": {
                "type": "Identifier",
                "start": 1791,
                "end": 1794,
                "loc": {
                  "start": {
                    "line": 40,
                    "column": 13
                  },
                  "end": {
                    "line": 40,
                    "column": 16
                  },
                  "identifierName": "Box"
                },
                "name": "Box",
                "leadingComments": null
              },
              "init": {
                "type": "ArrowFunctionExpression",
                "start": 1797,
                "end": 1942,
                "loc": {
                  "start": {
                    "line": 40,
                    "column": 19
                  },
                  "end": {
                    "line": 49,
                    "column": 2
                  }
                },
                "id": {
                  "type": "Identifier",
                  "start": 1791,
                  "end": 1794,
                  "loc": {
                    "start": {
                      "line": 40,
                      "column": 13
                    },
                    "end": {
                      "line": 40,
                      "column": 16
                    },
                    "identifierName": "Box"
                  },
                  "name": "Box",
                  "leadingComments": null
                },
                "generator": false,
                "expression": true,
                "async": false,
                "params": [
                  {
                    "type": "Identifier",
                    "start": 1798,
                    "end": 1803,
                    "loc": {
                      "start": {
                        "line": 40,
                        "column": 20
                      },
                      "end": {
                        "line": 40,
                        "column": 25
                      },
                      "identifierName": "props"
                    },
                    "name": "props"
                  },
                  {
                    "type": "Identifier",
                    "start": 1805,
                    "end": 1813,
                    "loc": {
                      "start": {
                        "line": 40,
                        "column": 27
                      },
                      "end": {
                        "line": 40,
                        "column": 35
                      },
                      "identifierName": "children"
                    },
                    "name": "children"
                  }
                ],
                "body": {
                  "type": "CallExpression",
                  "start": 1819,
                  "end": 1942,
                  "loc": {
                    "start": {
                      "line": 41,
                      "column": 1
                    },
                    "end": {
                      "line": 49,
                      "column": 2
                    }
                  },
                  "callee": {
                    "type": "Identifier",
                    "start": 1819,
                    "end": 1820,
                    "loc": {
                      "start": {
                        "line": 41,
                        "column": 1
                      },
                      "end": {
                        "line": 41,
                        "column": 2
                      },
                      "identifierName": "h"
                    },
                    "name": "h"
                  },
                  "arguments": [
                    {
                      "type": "Identifier",
                      "start": 1824,
                      "end": 1831,
                      "loc": {
                        "start": {
                          "line": 42,
                          "column": 2
                        },
                        "end": {
                          "line": 42,
                          "column": 9
                        },
                        "identifierName": "Element"
                      },
                      "name": "Element"
                    },
                    {
                      "type": "ObjectExpression",
                      "start": 1835,
                      "end": 1927,
                      "loc": {
                        "start": {
                          "line": 43,
                          "column": 2
                        },
                        "end": {
                          "line": 47,
                          "column": 3
                        }
                      },
                      "properties": [
                        {
                          "type": "ObjectProperty",
                          "start": 1840,
                          "end": 1865,
                          "loc": {
                            "start": {
                              "line": 44,
                              "column": 3
                            },
                            "end": {
                              "line": 44,
                              "column": 28
                            }
                          },
                          "method": false,
                          "shorthand": false,
                          "computed": false,
                          "key": {
                            "type": "Identifier",
                            "start": 1840,
                            "end": 1851,
                            "loc": {
                              "start": {
                                "line": 44,
                                "column": 3
                              },
                              "end": {
                                "line": 44,
                                "column": 14
                              },
                              "identifierName": "orientation"
                            },
                            "name": "orientation"
                          },
                          "value": {
                            "type": "StringLiteral",
                            "start": 1853,
                            "end": 1865,
                            "loc": {
                              "start": {
                                "line": 44,
                                "column": 16
                              },
                              "end": {
                                "line": 44,
                                "column": 28
                              }
                            },
                            "extra": {
                              "rawValue": "horizontal",
                              "raw": "\"horizontal\""
                            },
                            "value": "horizontal"
                          }
                        },
                        {
                          "type": "SpreadProperty",
                          "start": 1870,
                          "end": 1878,
                          "loc": {
                            "start": {
                              "line": 45,
                              "column": 3
                            },
                            "end": {
                              "line": 45,
                              "column": 11
                            }
                          },
                          "argument": {
                            "type": "Identifier",
                            "start": 1873,
                            "end": 1878,
                            "loc": {
                              "start": {
                                "line": 45,
                                "column": 6
                              },
                              "end": {
                                "line": 45,
                                "column": 11
                              },
                              "identifierName": "props"
                            },
                            "name": "props"
                          }
                        },
                        {
                          "type": "ObjectProperty",
                          "start": 1883,
                          "end": 1922,
                          "loc": {
                            "start": {
                              "line": 46,
                              "column": 3
                            },
                            "end": {
                              "line": 46,
                              "column": 42
                            }
                          },
                          "method": false,
                          "shorthand": false,
                          "computed": false,
                          "key": {
                            "type": "Identifier",
                            "start": 1883,
                            "end": 1888,
                            "loc": {
                              "start": {
                                "line": 46,
                                "column": 3
                              },
                              "end": {
                                "line": 46,
                                "column": 8
                              },
                              "identifierName": "class"
                            },
                            "name": "class"
                          },
                          "value": {
                            "type": "ArrayExpression",
                            "start": 1890,
                            "end": 1922,
                            "loc": {
                              "start": {
                                "line": 46,
                                "column": 10
                              },
                              "end": {
                                "line": 46,
                                "column": 42
                              }
                            },
                            "elements": [
                              {
                                "type": "StringLiteral",
                                "start": 1891,
                                "end": 1908,
                                "loc": {
                                  "start": {
                                    "line": 46,
                                    "column": 11
                                  },
                                  "end": {
                                    "line": 46,
                                    "column": 28
                                  }
                                },
                                "extra": {
                                  "rawValue": "meeseOS-gui-box",
                                  "raw": "\"meeseOS-gui-box\""
                                },
                                "value": "meeseOS-gui-box"
                              },
                              {
                                "type": "MemberExpression",
                                "start": 1910,
                                "end": 1921,
                                "loc": {
                                  "start": {
                                    "line": 46,
                                    "column": 30
                                  },
                                  "end": {
                                    "line": 46,
                                    "column": 41
                                  }
                                },
                                "object": {
                                  "type": "Identifier",
                                  "start": 1910,
                                  "end": 1915,
                                  "loc": {
                                    "start": {
                                      "line": 46,
                                      "column": 30
                                    },
                                    "end": {
                                      "line": 46,
                                      "column": 35
                                    },
                                    "identifierName": "props"
                                  },
                                  "name": "props"
                                },
                                "property": {
                                  "type": "Identifier",
                                  "start": 1916,
                                  "end": 1921,
                                  "loc": {
                                    "start": {
                                      "line": 46,
                                      "column": 36
                                    },
                                    "end": {
                                      "line": 46,
                                      "column": 41
                                    },
                                    "identifierName": "class"
                                  },
                                  "name": "class"
                                },
                                "computed": false
                              }
                            ]
                          }
                        }
                      ]
                    },
                    {
                      "type": "Identifier",
                      "start": 1931,
                      "end": 1939,
                      "loc": {
                        "start": {
                          "line": 48,
                          "column": 2
                        },
                        "end": {
                          "line": 48,
                          "column": 10
                        },
                        "identifierName": "children"
                      },
                      "name": "children"
                    }
                  ]
                }
              },
              "leadingComments": null
            }
          ],
          "kind": "const",
          "leadingComments": [
            {
              "type": "CommentBlock",
              "value": "*\n * A flexbox\n * @param {BoxProperties} props Properties\n * @param {string} [props.orientation='horizontal'] Box orientation\n * @param {h[]} children Children\n ",
              "start": 1612,
              "end": 1777,
              "loc": {
                "start": {
                  "line": 34,
                  "column": 0
                },
                "end": {
                  "line": 39,
                  "column": 3
                }
              }
            }
          ],
          "trailingComments": []
        },
        "leadingComments": [
          {
            "type": "CommentBlock",
            "value": "*\n * A flexbox\n * @param {BoxProperties} props Properties\n * @param {string} [props.orientation='horizontal'] Box orientation\n * @param {h[]} children Children\n ",
            "start": 1612,
            "end": 1777,
            "loc": {
              "start": {
                "line": 34,
                "column": 0
              },
              "end": {
                "line": 39,
                "column": 3
              }
            }
          }
        ]
      }
    ],
    "directives": []
  },
  "comments": [
    {
      "type": "CommentBlock",
      "value": "*\n * OS.js - JavaScript Cloud/Web Desktop Platform\n *\n * Copyright (c) 2011-2020, Anders Evenrud <andersevenrud@gmail.com>\n * All rights reserved.\n *\n * Redistribution and use in source and binary forms, with or without\n * modification, are permitted provided that the following conditions are met:\n *\n * 1. Redistributions of source code must retain the above copyright notice, this\n *    list of conditions and the following disclaimer\n * 2. Redistributions in binary form must reproduce the above copyright notice,\n *    this list of conditions and the following disclaimer in the documentation\n *    and/or other materials provided with the distribution\n *\n * THIS SOFTWARE IS PROVIDED BY THE COPYRIGHT HOLDERS AND CONTRIBUTORS \"AS IS\" AND\n * ANY EXPRESS OR IMPLIED WARRANTIES, INCLUDING, BUT NOT LIMITED TO, THE IMPLIED\n * WARRANTIES OF MERCHANTABILITY AND FITNESS FOR A PARTICULAR PURPOSE ARE\n * DISCLAIMED. IN NO EVENT SHALL THE COPYRIGHT OWNER OR CONTRIBUTORS BE LIABLE FOR\n * ANY DIRECT, INDIRECT, INCIDENTAL, SPECIAL, EXEMPLARY, OR CONSEQUENTIAL DAMAGES\n * (INCLUDING, BUT NOT LIMITED TO, PROCUREMENT OF SUBSTITUTE GOODS OR SERVICES;\n * LOSS OF USE, DATA, OR PROFITS; OR BUSINESS INTERRUPTION) HOWEVER CAUSED AND\n * ON ANY THEORY OF LIABILITY, WHETHER IN CONTRACT, STRICT LIABILITY, OR TORT\n * (INCLUDING NEGLIGENCE OR OTHERWISE) ARISING IN ANY WAY OUT OF THE USE OF THIS\n * SOFTWARE, EVEN IF ADVISED OF THE POSSIBILITY OF SUCH DAMAGE.\n *\n * @author  Anders Evenrud <andersevenrud@gmail.com>\n * @licence Simplified BSD License\n ",
      "start": 0,
      "end": 1542,
      "loc": {
        "start": {
          "line": 1,
          "column": 0
        },
        "end": {
          "line": 29,
          "column": 3
        }
      }
    },
    {
      "type": "CommentBlock",
      "value": "*\n * A flexbox\n * @param {BoxProperties} props Properties\n * @param {string} [props.orientation='horizontal'] Box orientation\n * @param {h[]} children Children\n ",
      "start": 1612,
      "end": 1777,
      "loc": {
        "start": {
          "line": 34,
          "column": 0
        },
        "end": {
          "line": 39,
          "column": 3
        }
      }
    }
  ],
  "tokens": [
    {
      "type": "CommentBlock",
      "value": "*\n * OS.js - JavaScript Cloud/Web Desktop Platform\n *\n * Copyright (c) 2011-2020, Anders Evenrud <andersevenrud@gmail.com>\n * All rights reserved.\n *\n * Redistribution and use in source and binary forms, with or without\n * modification, are permitted provided that the following conditions are met:\n *\n * 1. Redistributions of source code must retain the above copyright notice, this\n *    list of conditions and the following disclaimer\n * 2. Redistributions in binary form must reproduce the above copyright notice,\n *    this list of conditions and the following disclaimer in the documentation\n *    and/or other materials provided with the distribution\n *\n * THIS SOFTWARE IS PROVIDED BY THE COPYRIGHT HOLDERS AND CONTRIBUTORS \"AS IS\" AND\n * ANY EXPRESS OR IMPLIED WARRANTIES, INCLUDING, BUT NOT LIMITED TO, THE IMPLIED\n * WARRANTIES OF MERCHANTABILITY AND FITNESS FOR A PARTICULAR PURPOSE ARE\n * DISCLAIMED. IN NO EVENT SHALL THE COPYRIGHT OWNER OR CONTRIBUTORS BE LIABLE FOR\n * ANY DIRECT, INDIRECT, INCIDENTAL, SPECIAL, EXEMPLARY, OR CONSEQUENTIAL DAMAGES\n * (INCLUDING, BUT NOT LIMITED TO, PROCUREMENT OF SUBSTITUTE GOODS OR SERVICES;\n * LOSS OF USE, DATA, OR PROFITS; OR BUSINESS INTERRUPTION) HOWEVER CAUSED AND\n * ON ANY THEORY OF LIABILITY, WHETHER IN CONTRACT, STRICT LIABILITY, OR TORT\n * (INCLUDING NEGLIGENCE OR OTHERWISE) ARISING IN ANY WAY OUT OF THE USE OF THIS\n * SOFTWARE, EVEN IF ADVISED OF THE POSSIBILITY OF SUCH DAMAGE.\n *\n * @author  Anders Evenrud <andersevenrud@gmail.com>\n * @licence Simplified BSD License\n ",
      "start": 0,
      "end": 1542,
      "loc": {
        "start": {
          "line": 1,
          "column": 0
        },
        "end": {
          "line": 29,
          "column": 3
        }
      }
    },
    {
      "type": {
        "label": "import",
        "keyword": "import",
        "beforeExpr": false,
        "startsExpr": true,
        "rightAssociative": false,
        "isLoop": false,
        "isAssign": false,
        "prefix": false,
        "postfix": false,
        "binop": null,
        "updateContext": null
      },
      "value": "import",
      "start": 1544,
      "end": 1550,
      "loc": {
        "start": {
          "line": 31,
          "column": 0
        },
        "end": {
          "line": 31,
          "column": 6
        }
      }
    },
    {
      "type": {
        "label": "{",
        "beforeExpr": true,
        "startsExpr": true,
        "rightAssociative": false,
        "isLoop": false,
        "isAssign": false,
        "prefix": false,
        "postfix": false,
        "binop": null
      },
      "start": 1551,
      "end": 1552,
      "loc": {
        "start": {
          "line": 31,
          "column": 7
        },
        "end": {
          "line": 31,
          "column": 8
        }
      }
    },
    {
      "type": {
        "label": "name",
        "beforeExpr": false,
        "startsExpr": true,
        "rightAssociative": false,
        "isLoop": false,
        "isAssign": false,
        "prefix": false,
        "postfix": false,
        "binop": null
      },
      "value": "Element",
      "start": 1553,
      "end": 1560,
      "loc": {
        "start": {
          "line": 31,
          "column": 9
        },
        "end": {
          "line": 31,
          "column": 16
        }
      }
    },
    {
      "type": {
        "label": "}",
        "beforeExpr": false,
        "startsExpr": false,
        "rightAssociative": false,
        "isLoop": false,
        "isAssign": false,
        "prefix": false,
        "postfix": false,
        "binop": null
      },
      "start": 1561,
      "end": 1562,
      "loc": {
        "start": {
          "line": 31,
          "column": 17
        },
        "end": {
          "line": 31,
          "column": 18
        }
      }
    },
    {
      "type": {
        "label": "name",
        "beforeExpr": false,
        "startsExpr": true,
        "rightAssociative": false,
        "isLoop": false,
        "isAssign": false,
        "prefix": false,
        "postfix": false,
        "binop": null
      },
      "value": "from",
      "start": 1563,
      "end": 1567,
      "loc": {
        "start": {
          "line": 31,
          "column": 19
        },
        "end": {
          "line": 31,
          "column": 23
        }
      }
    },
    {
      "type": {
        "label": "string",
        "beforeExpr": false,
        "startsExpr": true,
        "rightAssociative": false,
        "isLoop": false,
        "isAssign": false,
        "prefix": false,
        "postfix": false,
        "binop": null,
        "updateContext": null
      },
      "value": "./Element",
      "start": 1568,
      "end": 1579,
      "loc": {
        "start": {
          "line": 31,
          "column": 24
        },
        "end": {
          "line": 31,
          "column": 35
        }
      }
    },
    {
      "type": {
        "label": ";",
        "beforeExpr": true,
        "startsExpr": false,
        "rightAssociative": false,
        "isLoop": false,
        "isAssign": false,
        "prefix": false,
        "postfix": false,
        "binop": null,
        "updateContext": null
      },
      "start": 1579,
      "end": 1580,
      "loc": {
        "start": {
          "line": 31,
          "column": 35
        },
        "end": {
          "line": 31,
          "column": 36
        }
      }
    },
    {
      "type": {
        "label": "import",
        "keyword": "import",
        "beforeExpr": false,
        "startsExpr": true,
        "rightAssociative": false,
        "isLoop": false,
        "isAssign": false,
        "prefix": false,
        "postfix": false,
        "binop": null,
        "updateContext": null
      },
      "value": "import",
      "start": 1581,
      "end": 1587,
      "loc": {
        "start": {
          "line": 32,
          "column": 0
        },
        "end": {
          "line": 32,
          "column": 6
        }
      }
    },
    {
      "type": {
        "label": "{",
        "beforeExpr": true,
        "startsExpr": true,
        "rightAssociative": false,
        "isLoop": false,
        "isAssign": false,
        "prefix": false,
        "postfix": false,
        "binop": null
      },
      "start": 1588,
      "end": 1589,
      "loc": {
        "start": {
          "line": 32,
          "column": 7
        },
        "end": {
          "line": 32,
          "column": 8
        }
      }
    },
    {
      "type": {
        "label": "name",
        "beforeExpr": false,
        "startsExpr": true,
        "rightAssociative": false,
        "isLoop": false,
        "isAssign": false,
        "prefix": false,
        "postfix": false,
        "binop": null
      },
      "value": "h",
      "start": 1590,
      "end": 1591,
      "loc": {
        "start": {
          "line": 32,
          "column": 9
        },
        "end": {
          "line": 32,
          "column": 10
        }
      }
    },
    {
      "type": {
        "label": "}",
        "beforeExpr": false,
        "startsExpr": false,
        "rightAssociative": false,
        "isLoop": false,
        "isAssign": false,
        "prefix": false,
        "postfix": false,
        "binop": null
      },
      "start": 1592,
      "end": 1593,
      "loc": {
        "start": {
          "line": 32,
          "column": 11
        },
        "end": {
          "line": 32,
          "column": 12
        }
      }
    },
    {
      "type": {
        "label": "name",
        "beforeExpr": false,
        "startsExpr": true,
        "rightAssociative": false,
        "isLoop": false,
        "isAssign": false,
        "prefix": false,
        "postfix": false,
        "binop": null
      },
      "value": "from",
      "start": 1594,
      "end": 1598,
      "loc": {
        "start": {
          "line": 32,
          "column": 13
        },
        "end": {
          "line": 32,
          "column": 17
        }
      }
    },
    {
      "type": {
        "label": "string",
        "beforeExpr": false,
        "startsExpr": true,
        "rightAssociative": false,
        "isLoop": false,
        "isAssign": false,
        "prefix": false,
        "postfix": false,
        "binop": null,
        "updateContext": null
      },
      "value": "hyperapp",
      "start": 1599,
      "end": 1609,
      "loc": {
        "start": {
          "line": 32,
          "column": 18
        },
        "end": {
          "line": 32,
          "column": 28
        }
      }
    },
    {
      "type": {
        "label": ";",
        "beforeExpr": true,
        "startsExpr": false,
        "rightAssociative": false,
        "isLoop": false,
        "isAssign": false,
        "prefix": false,
        "postfix": false,
        "binop": null,
        "updateContext": null
      },
      "start": 1609,
      "end": 1610,
      "loc": {
        "start": {
          "line": 32,
          "column": 28
        },
        "end": {
          "line": 32,
          "column": 29
        }
      }
    },
    {
      "type": "CommentBlock",
      "value": "*\n * A flexbox\n * @param {BoxProperties} props Properties\n * @param {string} [props.orientation='horizontal'] Box orientation\n * @param {h[]} children Children\n ",
      "start": 1612,
      "end": 1777,
      "loc": {
        "start": {
          "line": 34,
          "column": 0
        },
        "end": {
          "line": 39,
          "column": 3
        }
      }
    },
    {
      "type": {
        "label": "export",
        "keyword": "export",
        "beforeExpr": false,
        "startsExpr": false,
        "rightAssociative": false,
        "isLoop": false,
        "isAssign": false,
        "prefix": false,
        "postfix": false,
        "binop": null,
        "updateContext": null
      },
      "value": "export",
      "start": 1778,
      "end": 1784,
      "loc": {
        "start": {
          "line": 40,
          "column": 0
        },
        "end": {
          "line": 40,
          "column": 6
        }
      }
    },
    {
      "type": {
        "label": "const",
        "keyword": "const",
        "beforeExpr": false,
        "startsExpr": false,
        "rightAssociative": false,
        "isLoop": false,
        "isAssign": false,
        "prefix": false,
        "postfix": false,
        "binop": null,
        "updateContext": null
      },
      "value": "const",
      "start": 1785,
      "end": 1790,
      "loc": {
        "start": {
          "line": 40,
          "column": 7
        },
        "end": {
          "line": 40,
          "column": 12
        }
      }
    },
    {
      "type": {
        "label": "name",
        "beforeExpr": false,
        "startsExpr": true,
        "rightAssociative": false,
        "isLoop": false,
        "isAssign": false,
        "prefix": false,
        "postfix": false,
        "binop": null
      },
      "value": "Box",
      "start": 1791,
      "end": 1794,
      "loc": {
        "start": {
          "line": 40,
          "column": 13
        },
        "end": {
          "line": 40,
          "column": 16
        }
      }
    },
    {
      "type": {
        "label": "=",
        "beforeExpr": true,
        "startsExpr": false,
        "rightAssociative": false,
        "isLoop": false,
        "isAssign": true,
        "prefix": false,
        "postfix": false,
        "binop": null,
        "updateContext": null
      },
      "value": "=",
      "start": 1795,
      "end": 1796,
      "loc": {
        "start": {
          "line": 40,
          "column": 17
        },
        "end": {
          "line": 40,
          "column": 18
        }
      }
    },
    {
      "type": {
        "label": "(",
        "beforeExpr": true,
        "startsExpr": true,
        "rightAssociative": false,
        "isLoop": false,
        "isAssign": false,
        "prefix": false,
        "postfix": false,
        "binop": null
      },
      "start": 1797,
      "end": 1798,
      "loc": {
        "start": {
          "line": 40,
          "column": 19
        },
        "end": {
          "line": 40,
          "column": 20
        }
      }
    },
    {
      "type": {
        "label": "name",
        "beforeExpr": false,
        "startsExpr": true,
        "rightAssociative": false,
        "isLoop": false,
        "isAssign": false,
        "prefix": false,
        "postfix": false,
        "binop": null
      },
      "value": "props",
      "start": 1798,
      "end": 1803,
      "loc": {
        "start": {
          "line": 40,
          "column": 20
        },
        "end": {
          "line": 40,
          "column": 25
        }
      }
    },
    {
      "type": {
        "label": ",",
        "beforeExpr": true,
        "startsExpr": false,
        "rightAssociative": false,
        "isLoop": false,
        "isAssign": false,
        "prefix": false,
        "postfix": false,
        "binop": null,
        "updateContext": null
      },
      "start": 1803,
      "end": 1804,
      "loc": {
        "start": {
          "line": 40,
          "column": 25
        },
        "end": {
          "line": 40,
          "column": 26
        }
      }
    },
    {
      "type": {
        "label": "name",
        "beforeExpr": false,
        "startsExpr": true,
        "rightAssociative": false,
        "isLoop": false,
        "isAssign": false,
        "prefix": false,
        "postfix": false,
        "binop": null
      },
      "value": "children",
      "start": 1805,
      "end": 1813,
      "loc": {
        "start": {
          "line": 40,
          "column": 27
        },
        "end": {
          "line": 40,
          "column": 35
        }
      }
    },
    {
      "type": {
        "label": ")",
        "beforeExpr": false,
        "startsExpr": false,
        "rightAssociative": false,
        "isLoop": false,
        "isAssign": false,
        "prefix": false,
        "postfix": false,
        "binop": null
      },
      "start": 1813,
      "end": 1814,
      "loc": {
        "start": {
          "line": 40,
          "column": 35
        },
        "end": {
          "line": 40,
          "column": 36
        }
      }
    },
    {
      "type": {
        "label": "=>",
        "beforeExpr": true,
        "startsExpr": false,
        "rightAssociative": false,
        "isLoop": false,
        "isAssign": false,
        "prefix": false,
        "postfix": false,
        "binop": null,
        "updateContext": null
      },
      "start": 1815,
      "end": 1817,
      "loc": {
        "start": {
          "line": 40,
          "column": 37
        },
        "end": {
          "line": 40,
          "column": 39
        }
      }
    },
    {
      "type": {
        "label": "name",
        "beforeExpr": false,
        "startsExpr": true,
        "rightAssociative": false,
        "isLoop": false,
        "isAssign": false,
        "prefix": false,
        "postfix": false,
        "binop": null
      },
      "value": "h",
      "start": 1819,
      "end": 1820,
      "loc": {
        "start": {
          "line": 41,
          "column": 1
        },
        "end": {
          "line": 41,
          "column": 2
        }
      }
    },
    {
      "type": {
        "label": "(",
        "beforeExpr": true,
        "startsExpr": true,
        "rightAssociative": false,
        "isLoop": false,
        "isAssign": false,
        "prefix": false,
        "postfix": false,
        "binop": null
      },
      "start": 1820,
      "end": 1821,
      "loc": {
        "start": {
          "line": 41,
          "column": 2
        },
        "end": {
          "line": 41,
          "column": 3
        }
      }
    },
    {
      "type": {
        "label": "name",
        "beforeExpr": false,
        "startsExpr": true,
        "rightAssociative": false,
        "isLoop": false,
        "isAssign": false,
        "prefix": false,
        "postfix": false,
        "binop": null
      },
      "value": "Element",
      "start": 1824,
      "end": 1831,
      "loc": {
        "start": {
          "line": 42,
          "column": 2
        },
        "end": {
          "line": 42,
          "column": 9
        }
      }
    },
    {
      "type": {
        "label": ",",
        "beforeExpr": true,
        "startsExpr": false,
        "rightAssociative": false,
        "isLoop": false,
        "isAssign": false,
        "prefix": false,
        "postfix": false,
        "binop": null,
        "updateContext": null
      },
      "start": 1831,
      "end": 1832,
      "loc": {
        "start": {
          "line": 42,
          "column": 9
        },
        "end": {
          "line": 42,
          "column": 10
        }
      }
    },
    {
      "type": {
        "label": "{",
        "beforeExpr": true,
        "startsExpr": true,
        "rightAssociative": false,
        "isLoop": false,
        "isAssign": false,
        "prefix": false,
        "postfix": false,
        "binop": null
      },
      "start": 1835,
      "end": 1836,
      "loc": {
        "start": {
          "line": 43,
          "column": 2
        },
        "end": {
          "line": 43,
          "column": 3
        }
      }
    },
    {
      "type": {
        "label": "name",
        "beforeExpr": false,
        "startsExpr": true,
        "rightAssociative": false,
        "isLoop": false,
        "isAssign": false,
        "prefix": false,
        "postfix": false,
        "binop": null
      },
      "value": "orientation",
      "start": 1840,
      "end": 1851,
      "loc": {
        "start": {
          "line": 44,
          "column": 3
        },
        "end": {
          "line": 44,
          "column": 14
        }
      }
    },
    {
      "type": {
        "label": ":",
        "beforeExpr": true,
        "startsExpr": false,
        "rightAssociative": false,
        "isLoop": false,
        "isAssign": false,
        "prefix": false,
        "postfix": false,
        "binop": null,
        "updateContext": null
      },
      "start": 1851,
      "end": 1852,
      "loc": {
        "start": {
          "line": 44,
          "column": 14
        },
        "end": {
          "line": 44,
          "column": 15
        }
      }
    },
    {
      "type": {
        "label": "string",
        "beforeExpr": false,
        "startsExpr": true,
        "rightAssociative": false,
        "isLoop": false,
        "isAssign": false,
        "prefix": false,
        "postfix": false,
        "binop": null,
        "updateContext": null
      },
      "value": "horizontal",
      "start": 1853,
      "end": 1865,
      "loc": {
        "start": {
          "line": 44,
          "column": 16
        },
        "end": {
          "line": 44,
          "column": 28
        }
      }
    },
    {
      "type": {
        "label": ",",
        "beforeExpr": true,
        "startsExpr": false,
        "rightAssociative": false,
        "isLoop": false,
        "isAssign": false,
        "prefix": false,
        "postfix": false,
        "binop": null,
        "updateContext": null
      },
      "start": 1865,
      "end": 1866,
      "loc": {
        "start": {
          "line": 44,
          "column": 28
        },
        "end": {
          "line": 44,
          "column": 29
        }
      }
    },
    {
      "type": {
        "label": "...",
        "beforeExpr": true,
        "startsExpr": false,
        "rightAssociative": false,
        "isLoop": false,
        "isAssign": false,
        "prefix": false,
        "postfix": false,
        "binop": null,
        "updateContext": null
      },
      "start": 1870,
      "end": 1873,
      "loc": {
        "start": {
          "line": 45,
          "column": 3
        },
        "end": {
          "line": 45,
          "column": 6
        }
      }
    },
    {
      "type": {
        "label": "name",
        "beforeExpr": false,
        "startsExpr": true,
        "rightAssociative": false,
        "isLoop": false,
        "isAssign": false,
        "prefix": false,
        "postfix": false,
        "binop": null
      },
      "value": "props",
      "start": 1873,
      "end": 1878,
      "loc": {
        "start": {
          "line": 45,
          "column": 6
        },
        "end": {
          "line": 45,
          "column": 11
        }
      }
    },
    {
      "type": {
        "label": ",",
        "beforeExpr": true,
        "startsExpr": false,
        "rightAssociative": false,
        "isLoop": false,
        "isAssign": false,
        "prefix": false,
        "postfix": false,
        "binop": null,
        "updateContext": null
      },
      "start": 1878,
      "end": 1879,
      "loc": {
        "start": {
          "line": 45,
          "column": 11
        },
        "end": {
          "line": 45,
          "column": 12
        }
      }
    },
    {
      "type": {
        "label": "class",
        "keyword": "class",
        "beforeExpr": false,
        "startsExpr": false,
        "rightAssociative": false,
        "isLoop": false,
        "isAssign": false,
        "prefix": false,
        "postfix": false,
        "binop": null,
        "updateContext": null
      },
      "value": "class",
      "start": 1883,
      "end": 1888,
      "loc": {
        "start": {
          "line": 46,
          "column": 3
        },
        "end": {
          "line": 46,
          "column": 8
        }
      }
    },
    {
      "type": {
        "label": ":",
        "beforeExpr": true,
        "startsExpr": false,
        "rightAssociative": false,
        "isLoop": false,
        "isAssign": false,
        "prefix": false,
        "postfix": false,
        "binop": null,
        "updateContext": null
      },
      "start": 1888,
      "end": 1889,
      "loc": {
        "start": {
          "line": 46,
          "column": 8
        },
        "end": {
          "line": 46,
          "column": 9
        }
      }
    },
    {
      "type": {
        "label": "[",
        "beforeExpr": true,
        "startsExpr": true,
        "rightAssociative": false,
        "isLoop": false,
        "isAssign": false,
        "prefix": false,
        "postfix": false,
        "binop": null,
        "updateContext": null
      },
      "start": 1890,
      "end": 1891,
      "loc": {
        "start": {
          "line": 46,
          "column": 10
        },
        "end": {
          "line": 46,
          "column": 11
        }
      }
    },
    {
      "type": {
        "label": "string",
        "beforeExpr": false,
        "startsExpr": true,
        "rightAssociative": false,
        "isLoop": false,
        "isAssign": false,
        "prefix": false,
        "postfix": false,
        "binop": null,
        "updateContext": null
      },
      "value": "meeseOS-gui-box",
      "start": 1891,
      "end": 1908,
      "loc": {
        "start": {
          "line": 46,
          "column": 11
        },
        "end": {
          "line": 46,
          "column": 28
        }
      }
    },
    {
      "type": {
        "label": ",",
        "beforeExpr": true,
        "startsExpr": false,
        "rightAssociative": false,
        "isLoop": false,
        "isAssign": false,
        "prefix": false,
        "postfix": false,
        "binop": null,
        "updateContext": null
      },
      "start": 1908,
      "end": 1909,
      "loc": {
        "start": {
          "line": 46,
          "column": 28
        },
        "end": {
          "line": 46,
          "column": 29
        }
      }
    },
    {
      "type": {
        "label": "name",
        "beforeExpr": false,
        "startsExpr": true,
        "rightAssociative": false,
        "isLoop": false,
        "isAssign": false,
        "prefix": false,
        "postfix": false,
        "binop": null
      },
      "value": "props",
      "start": 1910,
      "end": 1915,
      "loc": {
        "start": {
          "line": 46,
          "column": 30
        },
        "end": {
          "line": 46,
          "column": 35
        }
      }
    },
    {
      "type": {
        "label": ".",
        "beforeExpr": false,
        "startsExpr": false,
        "rightAssociative": false,
        "isLoop": false,
        "isAssign": false,
        "prefix": false,
        "postfix": false,
        "binop": null,
        "updateContext": null
      },
      "start": 1915,
      "end": 1916,
      "loc": {
        "start": {
          "line": 46,
          "column": 35
        },
        "end": {
          "line": 46,
          "column": 36
        }
      }
    },
    {
      "type": {
        "label": "class",
        "keyword": "class",
        "beforeExpr": false,
        "startsExpr": false,
        "rightAssociative": false,
        "isLoop": false,
        "isAssign": false,
        "prefix": false,
        "postfix": false,
        "binop": null,
        "updateContext": null
      },
      "value": "class",
      "start": 1916,
      "end": 1921,
      "loc": {
        "start": {
          "line": 46,
          "column": 36
        },
        "end": {
          "line": 46,
          "column": 41
        }
      }
    },
    {
      "type": {
        "label": "]",
        "beforeExpr": false,
        "startsExpr": false,
        "rightAssociative": false,
        "isLoop": false,
        "isAssign": false,
        "prefix": false,
        "postfix": false,
        "binop": null,
        "updateContext": null
      },
      "start": 1921,
      "end": 1922,
      "loc": {
        "start": {
          "line": 46,
          "column": 41
        },
        "end": {
          "line": 46,
          "column": 42
        }
      }
    },
    {
      "type": {
        "label": ",",
        "beforeExpr": true,
        "startsExpr": false,
        "rightAssociative": false,
        "isLoop": false,
        "isAssign": false,
        "prefix": false,
        "postfix": false,
        "binop": null,
        "updateContext": null
      },
      "start": 1922,
      "end": 1923,
      "loc": {
        "start": {
          "line": 46,
          "column": 42
        },
        "end": {
          "line": 46,
          "column": 43
        }
      }
    },
    {
      "type": {
        "label": "}",
        "beforeExpr": false,
        "startsExpr": false,
        "rightAssociative": false,
        "isLoop": false,
        "isAssign": false,
        "prefix": false,
        "postfix": false,
        "binop": null
      },
      "start": 1926,
      "end": 1927,
      "loc": {
        "start": {
          "line": 47,
          "column": 2
        },
        "end": {
          "line": 47,
          "column": 3
        }
      }
    },
    {
      "type": {
        "label": ",",
        "beforeExpr": true,
        "startsExpr": false,
        "rightAssociative": false,
        "isLoop": false,
        "isAssign": false,
        "prefix": false,
        "postfix": false,
        "binop": null,
        "updateContext": null
      },
      "start": 1927,
      "end": 1928,
      "loc": {
        "start": {
          "line": 47,
          "column": 3
        },
        "end": {
          "line": 47,
          "column": 4
        }
      }
    },
    {
      "type": {
        "label": "name",
        "beforeExpr": false,
        "startsExpr": true,
        "rightAssociative": false,
        "isLoop": false,
        "isAssign": false,
        "prefix": false,
        "postfix": false,
        "binop": null
      },
      "value": "children",
      "start": 1931,
      "end": 1939,
      "loc": {
        "start": {
          "line": 48,
          "column": 2
        },
        "end": {
          "line": 48,
          "column": 10
        }
      }
    },
    {
      "type": {
        "label": ")",
        "beforeExpr": false,
        "startsExpr": false,
        "rightAssociative": false,
        "isLoop": false,
        "isAssign": false,
        "prefix": false,
        "postfix": false,
        "binop": null
      },
      "start": 1941,
      "end": 1942,
      "loc": {
        "start": {
          "line": 49,
          "column": 1
        },
        "end": {
          "line": 49,
          "column": 2
        }
      }
    },
    {
      "type": {
        "label": ";",
        "beforeExpr": true,
        "startsExpr": false,
        "rightAssociative": false,
        "isLoop": false,
        "isAssign": false,
        "prefix": false,
        "postfix": false,
        "binop": null,
        "updateContext": null
      },
      "start": 1942,
      "end": 1943,
      "loc": {
        "start": {
          "line": 49,
          "column": 2
        },
        "end": {
          "line": 49,
          "column": 3
        }
      }
    },
    {
      "type": {
        "label": "eof",
        "beforeExpr": false,
        "startsExpr": false,
        "rightAssociative": false,
        "isLoop": false,
        "isAssign": false,
        "prefix": false,
        "postfix": false,
        "binop": null,
        "updateContext": null
      },
      "start": 1944,
      "end": 1944,
      "loc": {
        "start": {
          "line": 50,
          "column": 0
        },
        "end": {
          "line": 50,
          "column": 0
        }
      }
    }
  ]
}